setup.py
evtol/__init__.py
evtol/constraint_analysis.py
evtol/optimization_problem.py
evtol/plotter.py
evtol/uav_data.py
evtol.egg-info/PKG-INFO
evtol.egg-info/SOURCES.txt
evtol.egg-info/dependency_links.txt
evtol.egg-info/top_level.txt