Metadata-Version: 1.0
Name: evtol
Version: 0.0
Summary: Fixed wing - VTOL Sizing module
Home-page: UNKNOWN
Author: Rano Veder, Lorenzo Terenzi, Jose Ignacio de Alvear Cardenas
Author-email: UNKNOWN
License: UNKNOWN
Platform: UNKNOWN
